{
  "tasks": [
    {
      "id": "1531",
      "solidername": "احمد علي رمضان خضر",
      "phonenumber": "01015036158",
      "qualification": "3",
      "soliderrkm": "2991101414457",
      "soliderSSn": "2991101414457",
      "soliderhome": "",
      "solidertagneed": "2024-04-24",
      "soliderendmam": "2024-04-26",
      "solidertsreeh": "2024-04-26",
      "department": "",
      "selectedGovernorate": "14",
      "selectedCity": "السويس",
      "iskowa": true,
      "address": "بنها"
    },
    {
      "id": "4e7d",
      "solidername": "dscfds",
      "phonenumber": "",
      "qualification": "",
      "soliderrkm": "",
      "soliderSSn": "",
      "soliderhome": "",
      "solidertagneed": "",
      "soliderendmam": "",
      "solidertsreeh": "",
      "department": "",
      "selectedGovernorate": "",
      "selectedCity": "",
      "iskowa": false
    },
    {
      "id": "8585",
      "solidername": "dscdscds",
      "phonenumber": "",
      "qualification": "",
      "soliderrkm": "",
      "soliderSSn": "",
      "soliderhome": "",
      "solidertagneed": "",
      "soliderendmam": "",
      "solidertsreeh": "",
      "department": "",
      "selectedGovernorate": "",
      "selectedCity": "",
      "iskowa": false
    },
    {
      "id": "490b",
      "solidername": "dscdscds",
      "phonenumber": "",
      "qualification": "",
      "soliderrkm": "",
      "soliderSSn": "",
      "soliderhome": "",
      "solidertagneed": "",
      "soliderendmam": "",
      "solidertsreeh": "",
      "department": "",
      "selectedGovernorate": "",
      "selectedCity": "",
      "iskowa": false
    }
  ],
  "saf": [],
  "department": [],
  "home": []
}